nvdinterface/__init__.py
nvdinterface/internal/Exceptions.py
nvdinterface/internal/NormalisedAPIParameters.py
nvdinterface/internal/__init__.py
nvdinterface/nvd_interface.py
nvdinterface/vuln_types/CVE.py
nvdinterface/vuln_types/CWE.py
nvdinterface/vuln_types/__init__.py
nvdinterface/vuln_types/property_types/ChangeItem.py
nvdinterface/vuln_types/property_types/Configurations.py
nvdinterface/vuln_types/property_types/Description.py
nvdinterface/vuln_types/property_types/Reference.py
nvdinterface/vuln_types/property_types/VendorComment.py
nvdinterface/vuln_types/property_types/Weakness.py
nvdinterface/vuln_types/property_types/__init__.py
nvdinterface/vuln_types/property_types/metrics/BaseCVSSMetric.py
nvdinterface/vuln_types/property_types/metrics/CVSSMetricV2.py
nvdinterface/vuln_types/property_types/metrics/CVSSMetricV30.py
nvdinterface/vuln_types/property_types/metrics/CVSSMetricV31.py
nvdinterface/vuln_types/property_types/metrics/CVSSMetricV40.py
nvdinterface/vuln_types/property_types/metrics/__init__.py
nvdinterface/vuln_types/property_types/metrics/helpers.py
nvdinterface-0.6.2.dist-info/LICENSE
nvdinterface-0.6.2.dist-info/METADATA
nvdinterface-0.6.2.dist-info/WHEEL
nvdinterface-0.6.2.dist-info/RECORD
