Metadata-Version: 2.3
Name: nvdinterface
Version: 0.6.2
Summary: An convenience python class for interacting with NVD
Author: Lachlan Jones
Requires-Python: >=3.11
Classifier: Programming Language :: Python :: 3
Classifier: Operating System :: OS Independent
Classifier: Development Status :: 2 - Pre-Alpha
Classifier: License :: OSI Approved :: GNU General Public License v3 (GPLv3)
Provides-Extra: dev
Requires-Dist: black (==25.1.0) ; extra == "dev"
Requires-Dist: datetime (==5.5)
Requires-Dist: iso639-lang (==2.6.3)
Requires-Dist: requests (==2.32.5)
Requires-Dist: sphinx (==8.2.3) ; extra == "dev"
Project-URL: Changelog, https://github.com/LachJones/nvdinterface/tags
Project-URL: Homepage, https://github.com/lachjones/nvdinterface
Project-URL: Issues, https://github.com/lachjones/nvdinterface/issues
Project-URL: Repository, https://github.com/lachjones/nvdinterface
